[
  {
    "id": 1,
    "title": "Country API",
    "description": "A web project where a list of countries are collected from an open API endpoint.",
    "type":"FrontEnd",
    "technologies": ["JavaScript", "ReactJs", "Redux", "Typescript", "Material-UI"],
    "image": "/countriesRestAPI.png",
    "demoLink": "https://responsive-countries-rest-api.netlify.app/",
    "codeLink": "https://github.com/mesfint/frontend-challenges/tree/main/rest-countries-api"
  },
  {
    "id": 2,
    "title": "Task Manager",
    "description": "CRUD  Application to manage personal tasks .",
    "type":"FrontEnd",
    "technologies": ["TypeScript", "ReactJs", "MUI", "Jest", "RTL"],
    "image": "/taskMgt.png",
    "demoLink": "https://task-mgt-dashboard.vercel.app/",
    "codeLink": "https://github.com/mesfint/task-mgt-dashboard"
  },
  {
    "id": 3,
    "title": "PhoneBook",
    "description": "A FullStack Application that registers contact name & phone number.",
    "type":"FullStack",
    "technologies": ["JavaScript", "ReactJs", "MongoDB", "ExpressJS","API"],
    "image": "/phoneBook.png",
    "demoLink": "https://fullstackopen-2024-phonebook.onrender.com/",
    "codeLink": "https://github.com/mesfin-2/Fullstackopen-2024/tree/main/part3/phonebook" 
  },
  {
    "id": 4,
    "title": "Portfolio Project",
    "description": " A modern and responsive portfolio website showcasing my web development skills and projects. Built using React, TypeScript, and Tailwind CSS to highlight clean design and user-friendly interactions..",
    "type":"FrontEnd",
    "technologies": ["ReactJs", "Tailwind CSS", "Typescript"],
    "image": "/portfolioDesign.png",
    "demoLink": "https://mesfin-git-main-mesfints-projects.vercel.app/",
    "codeLink": "https://github.com/mesfint/portfolio" 
  }


]
